flask_request_guid/__init__.py
flask_request_guid/py.typed
flask_request_guid-0.2.1.dist-info/LICENSE
flask_request_guid-0.2.1.dist-info/METADATA
flask_request_guid-0.2.1.dist-info/WHEEL
flask_request_guid-0.2.1.dist-info/top_level.txt
flask_request_guid-0.2.1.dist-info/RECORD
