Metadata-Version: 2.1
Name: flask-request-guid
Version: 0.2.1
Summary: Set a global UUID for each request in flask
Home-page: https://github.com/alexrudy/flask_request_guid
Author: Alex Rudy
Author-email: opensource@alexrudy.net
License: BSD license,
Classifier: Operating System :: OS Independent
Classifier: Programming Language :: Python
Classifier: Development Status :: 2 - Pre-Alpha
Classifier: Intended Audience :: Developers
Classifier: License :: OSI Approved :: BSD License
Classifier: Natural Language :: English
Classifier: Framework :: Flask
Classifier: Topic :: Utilities
Classifier: Typing :: Typed
Classifier: Programming Language :: Python :: 3
Classifier: Programming Language :: Python :: 3.9
Classifier: Programming Language :: Python :: 3.10
Classifier: Programming Language :: Python :: 3.11
Requires-Python: >=3.9
License-File: LICENSE
Requires-Dist: flask
